tex2lambda/__init__.py
tex2lambda/api/__init__.py
tex2lambda/api/module.py
tex2lambda/api/part.py
tex2lambda/api/question.py
tex2lambda/filters/PartPartSolSol/__init__.py
tex2lambda/filters/PartPartSolSol/example.tex
tex2lambda/filters/PartPartSolSol/filter.py
tex2lambda/filters/PartSolPartSol/__init__.py
tex2lambda/filters/PartSolPartSol/example.tex
tex2lambda/filters/PartSolPartSol/filter.py
tex2lambda/filters/PartsOneSol/__init__.py
tex2lambda/filters/PartsOneSol/example.tex
tex2lambda/filters/PartsOneSol/filter.py
tex2lambda/filters/PartsSepSol/__init__.py
tex2lambda/filters/PartsSepSol/example.tex
tex2lambda/filters/PartsSepSol/filter.py
tex2lambda/filters/__init__.py
tex2lambda/filters/_markdown.py
tex2lambda/json_convert/__init__.py
tex2lambda/json_convert/json_convert.py
tex2lambda/json_convert/minimal_template.json
tex2lambda/katex_convert/__init__.py
tex2lambda/katex_convert/delete_list.txt
tex2lambda/katex_convert/katex_convert(experimental)/katex_convert(experimental).py
tex2lambda/katex_convert/katex_convert(experimental)/latex_string.txt
tex2lambda/katex_convert/katex_convert(experimental)/prompt.txt
tex2lambda/katex_convert/katex_convert.py
tex2lambda/katex_convert/replace_list.txt
tex2lambda/main.py
tex2lambda/py.typed
tex2lambda-0.1.0.dist-info/LICENSE
tex2lambda-0.1.0.dist-info/METADATA
tex2lambda-0.1.0.dist-info/WHEEL
tex2lambda-0.1.0.dist-info/entry_points.txt
tex2lambda-0.1.0.dist-info/RECORD
