Metadata-Version: 2.1
Name: tex2lambda
Version: 0.1.0
Summary: 
License: MIT
Requires-Python: >=3.10,<4.0
Classifier: License :: OSI Approved :: MIT License
Classifier: Programming Language :: Python :: 3
Classifier: Programming Language :: Python :: 3.10
Classifier: Programming Language :: Python :: 3.11
Requires-Dist: beartype (>=0.15.0,<0.16.0)
Requires-Dist: panflute (>=2.3.0,<3.0.0)
Requires-Dist: rich-click (>=1.6.1,<2.0.0)
